thonnycontrib/kyanite_theme_syntax/__init__.py
thonnycontrib/kyanite_theme_ui/__init__.py
thonnycontrib/thonny-shoebot/__init__.py
thonnycontrib/thonny-shoebot/_version.py
thonnycontrib/thonny-shoebot/about_plugin.py
thonnycontrib/thonny-shoebot/py5colorpicker/tkcolorpicker/__init__.py
thonnycontrib/thonny-shoebot/py5colorpicker/tkcolorpicker/__main__.py
thonnycontrib/thonny-shoebot/py5colorpicker/tkcolorpicker/alphabar.py
thonnycontrib/thonny-shoebot/py5colorpicker/tkcolorpicker/colorpicker.py
thonnycontrib/thonny-shoebot/py5colorpicker/tkcolorpicker/colorsquare.py
thonnycontrib/thonny-shoebot/py5colorpicker/tkcolorpicker/functions.py
thonnycontrib/thonny-shoebot/py5colorpicker/tkcolorpicker/gradientbar.py
thonnycontrib/thonny-shoebot/py5colorpicker/tkcolorpicker/limitvar.py
thonnycontrib/thonny-shoebot/py5colorpicker/tkcolorpicker/spinbox.py
thonny_shoebot-0.1.0.dist-info/LICENSE
thonny_shoebot-0.1.0.dist-info/METADATA
thonny_shoebot-0.1.0.dist-info/WHEEL
thonny_shoebot-0.1.0.dist-info/top_level.txt
thonny_shoebot-0.1.0.dist-info/RECORD
