Metadata-Version: 2.1
Name: thonny-shoebot
Version: 0.1.0
Summary: shoebot plugin for Thonny
Home-page: https://github.com/shoebot/thonny-shoebot
Author: rlafuente
Author-email: r@manufacturaindependente.org
License: GPL
Classifier: Environment :: Plugins
Classifier: Topic :: Multimedia :: Graphics
Classifier: Topic :: Text Editors :: Integrated Development Environments (IDE)
License-File: LICENSE
Requires-Dist: shoebot (==1.4)
Requires-Dist: pyclip (==0.7.0)
Requires-Dist: pyperclip
